{"_ts":[1546326340],"_r":{"breakdown":{"html":{"bytes":[40209],"requests":[9]},"js":{"bytes":[292007],"requests":[21]},"css":{"bytes":[23914],"requests":[3]},"image":{"bytes":[110467],"requests":[13]},"flash":{"bytes":[0],"requests":[0]},"font":{"bytes":[108173],"requests":[7]},"video":{"bytes":[0],"requests":[0]},"other":{"bytes":[5659],"requests":[7]}},"date":[1546326340],"domElements":[1986.111111111111],"domInteractive":[599.7777777777778],"firstPaint":[624.3333333324001],"fullyLoaded":[2719.777777777778],"id":["190101_7K_9e5d50aae39b7f36275418b65c97d001"],"loadTime":[1992.3333333333333],"render":[611.1111111111111],"SpeedIndex":[853.1111111111111],"TTFB":[210.33333333333334],"videoFrames":[[{"_i":"ms_000000.jpg","_t":0,"_vc":0},{"_i":"ms_000600.jpg","_t":600,"_vc":46},{"_i":"ms_000700.jpg","_t":700,"_vc":46},{"_i":"ms_000800.jpg","_t":800,"_vc":52},{"_i":"ms_000900.jpg","_t":900,"_vc":61},{"_i":"ms_001000.jpg","_t":1000,"_vc":81},{"_i":"ms_001100.jpg","_t":1100,"_vc":91},{"_i":"ms_001200.jpg","_t":1200,"_vc":97},{"_i":"ms_001300.jpg","_t":1300,"_vc":93},{"_i":"ms_001400.jpg","_t":1400,"_vc":99},{"_i":"ms_001500.jpg","_t":1500,"_vc":100}]],"visualComplete":[1488.888888888889],"lighthouse":[57],"pagespeed":[86]}}